PyZohoBooksAPI/__init__.py
PyZohoBooksAPI/api/__init__.py
PyZohoBooksAPI/api/api.py
PyZohoBooksAPI/auth/__init__.py
PyZohoBooksAPI/auth/auth.py
PyZohoBooksAPI/contacts/__init__.py
PyZohoBooksAPI/contacts/contacts.py
PyZohoBooksAPI/invoices/__init__.py
PyZohoBooksAPI/invoices/invoices.py
PyZohoBooksAPI-0.0.1.dist-info/METADATA
PyZohoBooksAPI-0.0.1.dist-info/WHEEL
PyZohoBooksAPI-0.0.1.dist-info/top_level.txt
PyZohoBooksAPI-0.0.1.dist-info/RECORD
