Metadata-Version: 2.1
Name: PyZohoBooksAPI
Version: 0.0.1
Summary: Py Zoho Books API
Home-page: UNKNOWN
Author: marwan mohamed
Author-email: marawan6569@gmail.com
License: UNKNOWN
Keywords: python,API,zoho,zoho books
Platform: UNKNOWN
Classifier: Development Status :: 1 - Planning
Classifier: Intended Audience :: Developers
Classifier: Programming Language :: Python :: 3
Classifier: Operating System :: Unix
Classifier: Operating System :: MacOS :: MacOS X
Classifier: Operating System :: Microsoft :: Windows
Requires-Dist: requests
